pyLLS/__init__.py
pyLLS/_imputate.py
pyLLS-0.5.dist-info/LICENSE
pyLLS-0.5.dist-info/METADATA
pyLLS-0.5.dist-info/WHEEL
pyLLS-0.5.dist-info/top_level.txt
pyLLS-0.5.dist-info/RECORD
