Metadata-Version: 2.1
Name: pyLLS
Version: 0.5
Summary: Missing value imputation with the local least square algorithm in python
Home-page: https://github.com/osj118/pyLLS
Author: Sejin Oh
Author-email: Sejin Oh <agicic@naver.com>
Maintainer: Sejin Oh
License: MIT
Project-URL: Homepage, https://github.com/osj118/pyLLS
Keywords: missing value imputation,local least square
Classifier: Intended Audience :: Science/Research
Classifier: Programming Language :: Python :: 3
Classifier: Operating System :: OS Independent
Requires-Python: >=3.7
License-File: LICENSE
Requires-Dist: numpy
Requires-Dist: pandas
Requires-Dist: scikit-learn
Requires-Dist: tqdm
Requires-Dist: kneed
